predictserve/__init__.py
predictserve/predictserve.py
predictserve-0.1.0.dist-info/licenses/LICENSE
predictserve-0.1.0.dist-info/METADATA
predictserve-0.1.0.dist-info/WHEEL
predictserve-0.1.0.dist-info/top_level.txt
predictserve-0.1.0.dist-info/RECORD
