Metadata-Version: 2.4
Name: PredictServe
Version: 0.1.0
Summary: A Python package for advanced data classification.
Author-email: "Chinmay (Chish)" <chishxd@tutamail.com>
Project-URL: Homepage, https://github.com/chishxd/predictserve
Project-URL: Issues, https://github.com/chishxd/predictserve/issues
Classifier: Programming Language :: Python :: 3
Classifier: License :: OSI Approved :: MIT License
Classifier: Operating System :: OS Independent
Requires-Python: >=3.8
License-File: LICENSE
Dynamic: license-file
